[
  {
     "id":"/world",
     "name":"World",
     "url":"/world",
     "type":"section",
     "children":[
        {
           "id":"/world/africa",
           "name":"Africa",
           "url":"/world/africa"
        },
        {
           "id":"/world/americas",
           "name":"Americas",
           "url":"/world/americas"
        },
        {
           "id":"/world/asia-pacific",
           "name":"Asia Pacific",
           "url":"/world/asia-pacific"
        },
        {
           "id":"/world/china",
           "name":"China",
           "url":"/world/china"
        },
        {
           "id":"/world/europe",
           "name":"Europe",
           "url":"/world/europe"
        },
        {
           "id":"/world/india",
           "name":"India",
           "url":"/world/india"
        },
        {
           "id":"/world/middle-east",
           "name":"Middle East",
           "url":"/world/middle-east"
        },
        {
           "id":"/world/uk",
           "name":"United Kingdom",
           "url":"/world/uk"
        },
        {
           "id":"/world/us",
           "name":"United States",
           "url":"/world/us"
        },
        {
           "id":"/world/the-great-reboot",
           "name":"The Great Reboot",
           "url":"/world/the-great-reboot"
        },
        {
           "id":"/world/reuters-next",
           "name":"Reuters Next",
           "url":"/world/reuters-next"
        }
     ]
  },
  {
     "id":"/business",
     "name":"Business",
     "url":"/business",
     "type":"section",
     "children":[
        {
           "id":"/business/aerospace-defense",
           "name":"Aerospace & Defense",
           "url":"/business/aerospace-defense"
        },
        {
           "id":"/business/autos-transportation",
           "name":"Autos & Transportation",
           "url":"/business/autos-transportation"
        },
        {
           "id":"/business/energy",
           "name":"Energy",
           "url":"/business/energy"
        },
        {
           "id":"/business/environment",
           "name":"Environment",
           "url":"/business/environment"
        },
        {
           "id":"/business/finance",
           "name":"Finance",
           "url":"/business/finance"
        },
        {
           "id":"/business/healthcare-pharmaceuticals",
           "name":"Healthcare & Pharmaceuticals",
           "url":"/business/healthcare-pharmaceuticals"
        },
        {
           "id":"/business/media-telecom",
           "name":"Media & Telecom",
           "url":"/business/media-telecom"
        },
        {
           "id":"/business/retail-consumer",
           "name":"Retail & Consumer",
           "url":"/business/retail-consumer"
        },
        {
           "id":"/business/sustainable-business",
           "name":"Sustainable Business",
           "url":"/business/sustainable-business"
        },
        {
           "id":"/business/charged",
           "name":"Charged",
           "url":"/business/charged"
        },
        {
           "id":"/business/future-of-health",
           "name":"Future of Health",
           "url":"/business/future-of-health"
        },
        {
           "id":"/business/future-of-money",
           "name":"Future of Money",
           "url":"/business/future-of-money"
        },
        {
           "id":"/business/take-five",
           "name":"Take Five",
           "url":"/business/take-five"
        },
        {
           "id":"/business/reuters-impact",
           "name":"Reuters Impact",
           "url":"/business/reuters-impact"
        }
     ]
  },
  {
     "id":"/legal",
     "name":"Legal",
     "url":"/legal",
     "type":"section",
     "children":[
        {
           "id":"/legal/government",
           "name":"Government",
           "url":"/legal/government"
        },
        {
           "id":"/legal/legalindustry",
           "name":"Legal Industry",
           "url":"/legal/legalindustry"
        },
        {
           "id":"/legal/litigation",
           "name":"Litigation",
           "url":"/legal/litigation"
        },
        {
           "id":"/legal/transactional",
           "name":"Transactional",
           "url":"/legal/transactional"
        }
     ]
  },
  {
     "id":"/markets",
     "name":"Markets",
     "url":"/markets",
     "type":"section",
     "children":[
        {
           "id":"/markets/asia",
           "name":"Asian Markets",
           "url":"/markets/asia"
        },
        {
           "id":"/markets/carbon",
           "name":"Carbon Markets",
           "url":"/markets/carbon"
        },
        {
           "id":"/markets/commodities",
           "name":"Commodities",
           "url":"/markets/commodities"
        },
        {
           "id":"/markets/currencies",
           "name":"Currencies",
           "url":"/markets/currencies"
        },
        {
           "id":"/markets/deals",
           "name":"Deals",
           "url":"/markets/deals"
        },
        {
           "id":"/markets/emerging",
           "name":"Emerging Markets",
           "url":"/markets/emerging"
        },
        {
           "id":"/markets/europe",
           "name":"European Markets",
           "url":"/markets/europe"
        },
        {
           "id":"/markets/funds",
           "name":"Funds",
           "url":"/markets/funds"
        },
        {
           "id":"/markets/global-market-data",
           "name":"Global Market Data",
           "url":"/markets/global-market-data"
        },
        {
           "id":"/markets/rates-bonds",
           "name":"Rates & Bonds",
           "url":"/markets/rates-bonds"
        },
        {
           "id":"/markets/stocks",
           "name":"Stocks",
           "url":"/markets/stocks"
        },
        {
           "id":"/markets/us",
           "name":"U.S. Markets",
           "url":"/markets/us"
        },
        {
           "id":"/markets/wealth",
           "name":"Wealth",
           "url":"/markets/wealth"
        },
        {
           "id":"/markets/macromatters",
           "name":"Macro Matters",
           "url":"/markets/macromatters"
        }
     ]
  },
  {
     "id":"/breakingviews",
     "name":"Breakingviews",
     "url":"/breakingviews",
     "type":"section",
     "children":[

     ]
  },
  {
     "id":"/technology",
     "name":"Technology",
     "url":"/technology",
     "type":"section",
     "children":[
        {
           "id":"/technology/disrupted",
           "name":"Disrupted",
           "url":"/technology/disrupted"
        },
        {
           "id":"/technology/reuters-momentum",
           "name":"Reuters Momentum",
           "url":"/technology/reuters-momentum"
        }
     ]
  },
  {
     "id":"/investigates",
     "name":"Investigations",
     "url":"/investigates",
     "type":"section",
     "children":[

     ]
  },
  {
     "id":"/lifestyle/sports",
     "name":"Sports",
     "url":"/lifestyle/sports",
     "type":"section",
     "children":[
        {
           "id":"/lifestyle/sports/athletics",
           "name":"Athletics",
           "url":"/lifestyle/sports/athletics"
        },
        {
           "id":"/lifestyle/sports/cricket",
           "name":"Cricket",
           "url":"/lifestyle/sports/cricket"
        },
        {
           "id":"/lifestyle/sports/cycling",
           "name":"Cycling",
           "url":"/lifestyle/sports/cycling"
        },
        {
           "id":"/lifestyle/sports/golf",
           "name":"Golf",
           "url":"/lifestyle/sports/golf"
        },
        {
           "id":"/lifestyle/sports/motor-sports",
           "name":"Motor Sports",
           "url":"/lifestyle/sports/motor-sports"
        },
        {
           "id":"/lifestyle/sports/soccer",
           "name":"Soccer",
           "url":"/lifestyle/sports/soccer"
        },
        {
           "id":"/lifestyle/sports/tennis",
           "name":"Tennis",
           "url":"/lifestyle/sports/tennis"
        }
     ]
  },
  {
     "id":"/lifestyle",
     "name":"Lifestyle",
     "url":"/lifestyle",
     "type":"section",
     "children":[
        {
           "id":"/lifestyle/oddly-enough",
           "name":"Oddly Enough",
           "url":"/lifestyle/oddly-enough"
        },
        {
           "id":"/lifestyle/science",
           "name":"Science",
           "url":"/lifestyle/science"
        }
     ]
  },
  {
     "id":"/graphics",
     "name":"Graphics",
     "url":"/graphics",
     "type":"section",
     "children":[

     ]
  },
  {
     "id":"/pictures",
     "name":"Pictures",
     "url":"/pictures",
     "type":"section",
     "children":[

     ]
  },
  {
     "id":"/video",
     "name":"Video",
     "url":"/video",
     "type":"section",
     "children":[

     ]
  }
]